AUTHORS.txt
LICENSE.txt
MANIFEST.in
README.md
pyproject.toml
setup.py
src/EZGmail.egg-info/PKG-INFO
src/EZGmail.egg-info/SOURCES.txt
src/EZGmail.egg-info/dependency_links.txt
src/EZGmail.egg-info/requires.txt
src/EZGmail.egg-info/top_level.txt
src/ezgmail/__init__.py
src/ezgmail/__main__.py
tests/test_ezgmail.py