Metadata-Version: 2.4
Name: EZGmail
Version: 2025.11.11
Summary: A Pythonic interface to the Gmail API that actually works as of November 2025.
Home-page: https://github.com/asweigart/ezgmail
Author: Al Sweigart
Author-email: al@inventwithpython.com
License: GPLv3+
Classifier: License :: OSI Approved :: GNU General Public License v3 or later (GPLv3+)
Classifier: Programming Language :: Python
Classifier: Programming Language :: Python :: 3
Classifier: Programming Language :: Python :: 3.4
Classifier: Programming Language :: Python :: 3.5
Classifier: Programming Language :: Python :: 3.6
Classifier: Programming Language :: Python :: 3.7
Classifier: Programming Language :: Python :: 3.8
Classifier: Programming Language :: Python :: 3.9
Classifier: Programming Language :: Python :: 3.10
Classifier: Programming Language :: Python :: 3.11
License-File: LICENSE.txt
License-File: AUTHORS.txt
Requires-Dist: google-api-python-client
Requires-Dist: oauth2client
Dynamic: author
Dynamic: author-email
Dynamic: classifier
Dynamic: description
Dynamic: description-content-type
Dynamic: home-page
Dynamic: keywords
Dynamic: license
Dynamic: license-file
Dynamic: requires-dist
Dynamic: summary
